{
  "updated": "2026-07-08T16:25:11.124776+07:00",
  "topics": [
    {
      "topic": "teknologi",
      "article_count": 838,
      "recent_headlines": [
        "Kadima dan Matovu naik ring untuk kuasai kelas berat WBC Afrika",
        "Kemenpar perkuat event daerah untuk tarik minat wisatawan",
        "Pramono soroti peran Ikatan Wanita Pengusaha perkuat ekonomi daerah"
      ]
    },
    {
      "topic": "umum",
      "article_count": 551,
      "recent_headlines": [
        "Jakpus instruksikan kecamatan-kelurahan optimalisasi peran Satlinmas",
        "OJK pastikan tidak ada PHK massal di sektor perbankan nasional",
        "Taspen jelaskan laba 2025 turun karena pencadangan konservatif"
      ]
    },
    {
      "topic": "politik",
      "article_count": 419,
      "recent_headlines": [
        "Gubernur Jateng: Pembangunan daerah tak cukup andalkan APBD",
        "Kemenpar perkuat event daerah untuk tarik minat wisatawan",
        "Pramono soroti peran Ikatan Wanita Pengusaha perkuat ekonomi daerah"
      ]
    },
    {
      "topic": "sosial",
      "article_count": 235,
      "recent_headlines": [
        "Jokowi Bakal Hadir Langsung Sidang Dokter Tifa, Kuasa Hukum Bandingkan dengan Soeharto dan Habibie",
        "Nadiem daftarkan pengajuan banding vonis kasus Chromebook ke PN Jakpus",
        "Taspen dorong reformasi program jaminan sosial ASN"
      ]
    },
    {
      "topic": "ekonomi",
      "article_count": 210,
      "recent_headlines": [
        "Pramono soroti peran Ikatan Wanita Pengusaha perkuat ekonomi daerah",
        "Wamendagri Bima Arya Tegaskan Pentingnya Tata Ruang yang Baik untuk Kembangkan Potensi Kepri",
        "Negara D-8 perkuat kolaborasi wujudkan pusat ekonomi halal dunia"
      ]
    },
    {
      "topic": "internasional",
      "article_count": 184,
      "recent_headlines": [
        "IRGC: Serangan ke basis AS di Teluk balasan atas serangan ke Iran",
        "Informasi China terkait uji peluncuran rudal kapal bukti keterbukaan",
        "Presiden Prabowo lepas kepulangan PM Modi di Bandara YIA Yogyakarta"
      ]
    },
    {
      "topic": "olahraga",
      "article_count": 57,
      "recent_headlines": [
        "Tiga Nyeri Tak Wajar Setelah Olahraga yang Patut Diwaspadai",
        "Valencia resmi daratkan gelandang Ryunosuke Sato",
        "Paris FC tunjuk Liam Rosenior sebagai pelatih anyar"
      ]
    },
    {
      "topic": "hiburan",
      "article_count": 53,
      "recent_headlines": [
        "Update Ranking FIFA Hari Ini: Argentina Gagal Gusur Prancis Meski Menang Dramatis atas Mesir",
        "Gravity Game Unite Resmi Buka Open Beta Test Kedua Ragnarok Zero: Global untuk PC",
        "Argentina Menang Dramatis dari Mesir, Ibnu Jamil: Magic of Messi Masih Ada"
      ]
    }
  ]
}