{
  "updated": "2026-06-13T04:01:55.732849+07:00",
  "topics": [
    {
      "topic": "teknologi",
      "article_count": 627,
      "recent_headlines": [
        "Daftar Susunan Pemain Kanada vs Bosnia-Herzegovina",
        "Ekonom: Pertamax naik momentum evaluasi gaya hidup kelas menengah atas",
        "Ekonom sebut sejumlah syarat agar Kopdes handal sebagai pemasok MBG"
      ]
    },
    {
      "topic": "umum",
      "article_count": 338,
      "recent_headlines": [
        "Mario Lemos bidik target tinggi setelah kembali dipercaya Persijap",
        "PSIM Yogyakarta umumkan lepas Donny Warmerdam",
        "Kapuspen: pengerahan personel TNI guna jaga aksi demo tetap terkendali"
      ]
    },
    {
      "topic": "politik",
      "article_count": 332,
      "recent_headlines": [
        "Mendagri dorong DKPP tingkatkan integritas penyelenggara pemilu",
        "China larang Menhan Filipina masuk wilayahnya, termasuk HK dan Makau",
        "Mendagri imbau daerah nobar Piala Dunia 2026 untuk gerakkan ekonomi"
      ]
    },
    {
      "topic": "ekonomi",
      "article_count": 164,
      "recent_headlines": [
        "Ekonom: Pertamax naik momentum evaluasi gaya hidup kelas menengah atas",
        "Indonesia- China bahas potensi kerja sama AI dan ekonomi digital",
        "Mendagri imbau daerah nobar Piala Dunia 2026 untuk gerakkan ekonomi"
      ]
    },
    {
      "topic": "sosial",
      "article_count": 152,
      "recent_headlines": [
        "Tanah Datar alokasikan Rp600 juta untuk peternakan terdampak bencana",
        "Yusril: Kemitraan RI dan AS terus tumbuh dalam semangat saling hormat",
        "Kejagung tetapkan tersangka kelima kasus korupsi Makan Bergizi Gratis"
      ]
    },
    {
      "topic": "internasional",
      "article_count": 129,
      "recent_headlines": [
        "Indonesia- China bahas potensi kerja sama AI dan ekonomi digital",
        "China larang Menhan Filipina masuk wilayahnya, termasuk HK dan Makau",
        "Pemkot Solo kolaborasi ekonomi dan bisnis dengan Xi'an China"
      ]
    },
    {
      "topic": "olahraga",
      "article_count": 53,
      "recent_headlines": [
        "Dio Tirta: Peluang Dewa United Banten ke final IBL 2026 masih terbuka",
        "Thibodeaux: Percaya antarpemain jadi kunci Hornbills ke final IBL 2026",
        "Bagaimana Perasaan Saya Hari Ini? Pertanyaan Sederhana yang Hadir di Liga Kampus UniLeague 2026"
      ]
    },
    {
      "topic": "hiburan",
      "article_count": 38,
      "recent_headlines": [
        "Kejati Jabar jadwal ulang periksa Wabup Indramayu sebagai tersangka",
        "Tantangan Shareefa Daanish berperan dalam film horor \"Cerita Lila\"",
        "Kejati Jabar tetapkan Wakil Bupati Indramayu tersangka dugaan korupsi"
      ]
    }
  ]
}